{
  "db_name": "PostgreSQL",
  "query": "\n            select\n                backend_key.id as id,\n                backend_key.tag as tag,\n                backend_key.expires_at as expires_at,\n                backend_key.fencing_token as token,\n                backend_key.key_name as name,\n                now() as \"as_of!\"\n            from backend_key\n            left join backend on backend_key.id = backend.id\n            where backend_key.key_name = $1\n            and backend_key.namespace = $2\n            ",
  "describe": {
    "columns": [
      {
        "ordinal": 0,
        "name": "id",
        "type_info": "Varchar"
      },
      {
        "ordinal": 1,
        "name": "tag",
        "type_info": "Varchar"
      },
      {
        "ordinal": 2,
        "name": "expires_at",
        "type_info": "Timestamptz"
      },
      {
        "ordinal": 3,
        "name": "token",
        "type_info": "Int8"
      },
      {
        "ordinal": 4,
        "name": "name",
        "type_info": "Varchar"
      },
      {
        "ordinal": 5,
        "name": "as_of!",
        "type_info": "Timestamptz"
      }
    ],
    "parameters": {
      "Left": [
        "Text",
        "Text"
      ]
    },
    "nullable": [
      false,
      false,
      false,
      false,
      false,
      null
    ]
  },
  "hash": "f77eb5db0c9b07ded9a515ef3593ca6883e8ac711bcf7c353d9d1d50747d676a"
}
